parping/__init__.py
parping/main.py
parping/parping-cli.py
parping/parping.py
parping-0.0.2.dist-info/METADATA
parping-0.0.2.dist-info/WHEEL
parping-0.0.2.dist-info/licenses/LICENSE
parping-0.0.2.dist-info/RECORD
