Metadata-Version: 2.1
Name: parping
Version: 0.0.2
Summary: A simple parallel ipv4 ping utility
Project-URL: Homepage, https://github.com/dliebster/parping
Project-URL: Issues, https://github.com/dliebster/parping/issues
Author-email: Dan Liebster <daniel.liebster@gmail.com>
License-File: LICENSE
Classifier: License :: OSI Approved :: GNU General Public License v3 (GPLv3)
Classifier: Operating System :: OS Independent
Classifier: Programming Language :: Python :: 3
Requires-Python: >=3.8
